DiveIntoHtml5Zhongwenban/README.md
DiveIntoHtml5Zhongwenban/__init__.py
DiveIntoHtml5Zhongwenban/__main__.py
DiveIntoHtml5Zhongwenban/file.epub
DiveIntoHtml5Zhongwenban/index.html
DiveIntoHtml5Zhongwenban/css/__init__.py
DiveIntoHtml5Zhongwenban/css/annotations.css
DiveIntoHtml5Zhongwenban/css/main.css
DiveIntoHtml5Zhongwenban/css/normalize.css
DiveIntoHtml5Zhongwenban/css/popup.css
DiveIntoHtml5Zhongwenban/font/__init__.py
DiveIntoHtml5Zhongwenban/font/fontello.eot
DiveIntoHtml5Zhongwenban/font/fontello.svg
DiveIntoHtml5Zhongwenban/font/fontello.ttf
DiveIntoHtml5Zhongwenban/font/fontello.woff
DiveIntoHtml5Zhongwenban/img/__init__.py
DiveIntoHtml5Zhongwenban/img/annotator-glyph-sprite.png
DiveIntoHtml5Zhongwenban/img/annotator-icon-sprite.png
DiveIntoHtml5Zhongwenban/img/apple-touch-icon.png
DiveIntoHtml5Zhongwenban/img/cancelfullscreen.png
DiveIntoHtml5Zhongwenban/img/close.png
DiveIntoHtml5Zhongwenban/img/fullscreen.png
DiveIntoHtml5Zhongwenban/img/loader.gif
DiveIntoHtml5Zhongwenban/img/menu-icon.png
DiveIntoHtml5Zhongwenban/img/save.png
DiveIntoHtml5Zhongwenban/img/saved.png
DiveIntoHtml5Zhongwenban/img/settings-s.png
DiveIntoHtml5Zhongwenban/img/settings.png
DiveIntoHtml5Zhongwenban/img/star.png
DiveIntoHtml5Zhongwenban/js/__init__.py
DiveIntoHtml5Zhongwenban/js/epub.js
DiveIntoHtml5Zhongwenban/js/epub.min.js
DiveIntoHtml5Zhongwenban/js/epub.min.map
DiveIntoHtml5Zhongwenban/js/hooks.min.js
DiveIntoHtml5Zhongwenban/js/hooks.min.map
DiveIntoHtml5Zhongwenban/js/reader.js
DiveIntoHtml5Zhongwenban/js/reader.js.map
DiveIntoHtml5Zhongwenban/js/reader.min.js
DiveIntoHtml5Zhongwenban/js/reader.min.map
DiveIntoHtml5Zhongwenban/js/hooks/__init__.py
DiveIntoHtml5Zhongwenban/js/hooks/extensions/__init__.py
DiveIntoHtml5Zhongwenban/js/hooks/extensions/highlight.js
DiveIntoHtml5Zhongwenban/js/libs/__init__.py
DiveIntoHtml5Zhongwenban/js/libs/jquery.min.js
DiveIntoHtml5Zhongwenban/js/libs/localforage.min.js
DiveIntoHtml5Zhongwenban/js/libs/screenfull.js
dive_into_html5_zhongwenban-2024.3.4.0.dist-info/METADATA
dive_into_html5_zhongwenban-2024.3.4.0.dist-info/WHEEL
dive_into_html5_zhongwenban-2024.3.4.0.dist-info/entry_points.txt
dive_into_html5_zhongwenban-2024.3.4.0.dist-info/top_level.txt
dive_into_html5_zhongwenban-2024.3.4.0.dist-info/RECORD
